avx/CameraPosition.py
avx/Client.py
avx/PyroUtils.py
avx/Sequencer.py
avx/__init__.py
avx/_version.py
avx/utils.py
avx/controller/Controller.py
avx/controller/ControllerHttp.py
avx/controller/__init__.py
avx/controller/messagebus.py
avx/devices/Device.py
avx/devices/__init__.py
avx/devices/datavideo.py
avx/devices/net/Tivo.py
avx/devices/net/__init__.py
avx/devices/net/dvip.py
avx/devices/net/hyperdeck.py
avx/devices/net/milight.py
avx/devices/net/atem/__init__.py
avx/devices/net/atem/atem.py
avx/devices/net/atem/constants.py
avx/devices/net/atem/getter.py
avx/devices/net/atem/receiver.py
avx/devices/net/atem/sender.py
avx/devices/net/atem/utils.py
avx/devices/serial/CoriogenEclipse.py
avx/devices/serial/ETCUnison.py
avx/devices/serial/Inline3808.py
avx/devices/serial/Kramer602.py
avx/devices/serial/KramerVP703.py
avx/devices/serial/KramerVP88.py
avx/devices/serial/SerialDevice.py
avx/devices/serial/SerialRelayCard.py
avx/devices/serial/VISCACamera.py
avx/devices/serial/__init__.py
avx/devices/usb/__init__.py
avx/devices/usb/ambx.py
avx-1.6.0.dist-info/METADATA
avx-1.6.0.dist-info/WHEEL
avx-1.6.0.dist-info/entry_points.txt
avx-1.6.0.dist-info/top_level.txt
avx-1.6.0.dist-info/RECORD
